{
  "generated_at": "2026-01-22T04:49:03.802729",
  "total_drops": 547,
  "top_drops_shown": 100,
  "site_stats": [
    {
      "site": "fenwick_co_uk",
      "count": 234,
      "max_drop": 55.0,
      "total_savings": 4435.16
    },
    {
      "site": "johnlewis_com",
      "count": 299,
      "max_drop": 51.5,
      "total_savings": 8744.96
    },
    {
      "site": "dusk_com",
      "count": 3,
      "max_drop": 50.0,
      "total_savings": 45.0
    },
    {
      "site": "pigletinbed_com",
      "count": 1,
      "max_drop": 33.5,
      "total_savings": 56.0
    },
    {
      "site": "bugaboo_com",
      "count": 1,
      "max_drop": 28.0,
      "total_savings": 12.59
    },
    {
      "site": "flannels_com",
      "count": 3,
      "max_drop": 20.1,
      "total_savings": 91.99
    },
    {
      "site": "boden_com",
      "count": 4,
      "max_drop": 14.8,
      "total_savings": 7.3
    },
    {
      "site": "leaderonline_com",
      "count": 2,
      "max_drop": 8.2,
      "total_savings": 41.98
    }
  ],
  "drops": [
    {
      "site": "fenwick_co_uk",
      "product": "Jolene Waistcoat",
      "percentage": 55.0,
      "old_price": "60.00",
      "new_price": "27.00",
      "timestamp": "2026-01-22T04:48:39.399202",
      "url": "https://fenwick.co.uk/products/forever-new-light-coffee-suit-jolene-waistcoat"
    },
    {
      "site": "fenwick_co_uk",
      "product": "Panorama Duvet Cover",
      "percentage": 55.0,
      "old_price": "359.00",
      "new_price": "161.55",
      "timestamp": "2026-01-22T04:48:39.399202",
      "url": "https://fenwick.co.uk/products/other-multicoloured-panorama-duvet-cover-ydpanodcmulticoloured"
    },
    {
      "site": "fenwick_co_uk",
      "product": "Panorama Flat Sheet",
      "percentage": 55.0,
      "old_price": "269.00",
      "new_price": "121.05",
      "timestamp": "2026-01-22T04:48:39.399202",
      "url": "https://fenwick.co.uk/products/other-multicoloured-panorama-flat-sheet-ydpanofltmulticoloured"
    },
    {
      "site": "fenwick_co_uk",
      "product": "Givre Flat Sheet",
      "percentage": 55.0,
      "old_price": "255.00",
      "new_price": "114.75",
      "timestamp": "2026-01-22T04:48:39.399202",
      "url": "https://fenwick.co.uk/products/other-multicoloured-givre-flat-sheet"
    },
    {
      "site": "fenwick_co_uk",
      "product": "Etoile Bath Mat Collection",
      "percentage": 55.0,
      "old_price": "89.00",
      "new_price": "40.05",
      "timestamp": "2026-01-22T04:48:39.399202",
      "url": "https://fenwick.co.uk/products/other-silver-etoile-bath-mat-ydetoilesilverbm"
    },
    {
      "site": "fenwick_co_uk",
      "product": "Givre Cushion Cover",
      "percentage": 55.0,
      "old_price": "109.00",
      "new_price": "49.05",
      "timestamp": "2026-01-22T04:48:39.399202",
      "url": "https://fenwick.co.uk/products/other-multicoloured-givre-cushion-cover"
    },
    {
      "site": "fenwick_co_uk",
      "product": "Panorama Pillowcase",
      "percentage": 55.0,
      "old_price": "69.00",
      "new_price": "31.05",
      "timestamp": "2026-01-22T04:48:39.399202",
      "url": "https://fenwick.co.uk/products/other-multicoloured-panorama-pillowcase-ydpanopcmulticoloured"
    },
    {
      "site": "johnlewis_com",
      "product": "Kate Somerville Goat Milk Moisturising Cleanser, 120ml",
      "percentage": 51.5,
      "old_price": "41.00",
      "new_price": "19.89",
      "timestamp": "2026-01-22T00:48:54.704820",
      "url": "https://www.johnlewis.com/kate-somerville-goat-milk-moisturising-cleanser-120ml/p5153791"
    },
    {
      "site": "fenwick_co_uk",
      "product": "KGL LIVIAH",
      "percentage": 50.5,
      "old_price": "99.00",
      "new_price": "49.00",
      "timestamp": "2026-01-22T04:48:39.399202",
      "url": "https://fenwick.co.uk/products/silver-kgl-liviah-9480163109"
    },
    {
      "site": "johnlewis_com",
      "product": "Herschel Supply Co. Cove Messenger Bag, Black/Saddle Brown",
      "percentage": 50.0,
      "old_price": "75.00",
      "new_price": "37.50",
      "timestamp": "2026-01-22T00:48:54.704820",
      "url": "https://www.johnlewis.com/herschel-supply-co-cove-messenger-bag-black-saddle-brown/p113202207"
    },
    {
      "site": "johnlewis_com",
      "product": "Aspinal of London Hudson Leather Business Bag, Green",
      "percentage": 50.0,
      "old_price": "695.00",
      "new_price": "347.50",
      "timestamp": "2026-01-22T00:48:54.704820",
      "url": "https://www.johnlewis.com/aspinal-of-london-hudson-leather-business-bag-green/p113971992"
    },
    {
      "site": "dusk_com",
      "product": "Antigua Soft Fine Ribbed Towel Collection - Fern",
      "percentage": 50.0,
      "old_price": "10.00",
      "new_price": "5.00",
      "timestamp": "2026-01-22T01:59:08.917215",
      "url": "https://dusk.com/products/antigua-soft-fine-ribbed-towel-collection-fern"
    },
    {
      "site": "johnlewis_com",
      "product": "HUSH Grace A-Line Polka Dot Midi Dress",
      "percentage": 45.4,
      "old_price": "67.00",
      "new_price": "36.55",
      "timestamp": "2026-01-22T00:48:54.704820",
      "url": "https://www.johnlewis.com/hush-grace-a-line-polka-dot-midi-dress/p114107594"
    },
    {
      "site": "johnlewis_com",
      "product": "Mint Velvet Geometric Print Mini Dress, Black/Multi",
      "percentage": 44.9,
      "old_price": "89.00",
      "new_price": "49.00",
      "timestamp": "2026-01-22T00:48:54.704820",
      "url": "https://www.johnlewis.com/mint-velvet-geometric-print-mini-dress-black-multi/p114308218"
    },
    {
      "site": "johnlewis_com",
      "product": "Ro&Zo Petite Applique Knit Jumper Dress, Green",
      "percentage": 44.9,
      "old_price": "89.00",
      "new_price": "49.00",
      "timestamp": "2026-01-22T00:48:54.704820",
      "url": "https://www.johnlewis.com/ro-zo-petite-applique-knit-jumper-dress-green/p114060766"
    },
    {
      "site": "johnlewis_com",
      "product": "Kate Somerville Goat Milk Moisturising Cream, 50ml",
      "percentage": 44.6,
      "old_price": "72.00",
      "new_price": "39.86",
      "timestamp": "2026-01-22T00:48:54.704820",
      "url": "https://www.johnlewis.com/kate-somerville-goat-milk-moisturising-cream-50ml/p5149811"
    },
    {
      "site": "johnlewis_com",
      "product": "Carvela Jackpot Heeled Wide Fit Ankle Boots",
      "percentage": 44.0,
      "old_price": "159.00",
      "new_price": "89.00",
      "timestamp": "2026-01-22T04:48:56.172496",
      "url": "https://www.johnlewis.com/carvela-jackpot-heeled-wide-fit-ankle-boots/p113902511"
    },
    {
      "site": "johnlewis_com",
      "product": "Kurt Geiger London Sloane Leather Chelsea Boots",
      "percentage": 43.7,
      "old_price": "229.00",
      "new_price": "129.00",
      "timestamp": "2026-01-22T00:48:54.704820",
      "url": "https://www.johnlewis.com/kurt-geiger-london-sloane-leather-chelsea-boots/p112611407"
    },
    {
      "site": "fenwick_co_uk",
      "product": "SYMMETRY COURT VINYL 80",
      "percentage": 43.5,
      "old_price": "69.00",
      "new_price": "39.00",
      "timestamp": "2026-01-22T04:48:39.399202",
      "url": "https://fenwick.co.uk/products/gold-symmetry-court-vinyl-80-2413561979"
    },
    {
      "site": "johnlewis_com",
      "product": "John Lewis Asymmetric Chain Strap Clutch Bag, Deep Red",
      "percentage": 42.9,
      "old_price": "31.50",
      "new_price": "18.00",
      "timestamp": "2026-01-22T00:48:54.704820",
      "url": "https://www.johnlewis.com/john-lewis-asymmetric-chain-strap-clutch-bag-deep-red/p113904781"
    },
    {
      "site": "johnlewis_com",
      "product": "John Lewis Metallic Leather Passport Holder, Silver Croc",
      "percentage": 42.9,
      "old_price": "17.50",
      "new_price": "10.00",
      "timestamp": "2026-01-22T00:48:54.704820",
      "url": "https://www.johnlewis.com/john-lewis-metallic-leather-passport-holder-silver-croc/p113908516"
    },
    {
      "site": "johnlewis_com",
      "product": "French Connection Marina Sleeveless Mini Swing Dress",
      "percentage": 42.2,
      "old_price": "45.00",
      "new_price": "26.00",
      "timestamp": "2026-01-22T00:48:54.704820",
      "url": "https://www.johnlewis.com/french-connection-marina-sleeveless-mini-swing-dress/p113950590"
    },
    {
      "site": "johnlewis_com",
      "product": "Ro&Zo Jersey Tie Sleeveless Maxi Dress",
      "percentage": 40.8,
      "old_price": "49.00",
      "new_price": "29.00",
      "timestamp": "2026-01-22T00:48:54.704820",
      "url": "https://www.johnlewis.com/ro-zo-jersey-tie-sleeveless-maxi-dress/p113530393"
    },
    {
      "site": "johnlewis_com",
      "product": "Gallery Direct Carmel Arched Metal Frame Window Wall Mirror, 90 x 60cm",
      "percentage": 40.5,
      "old_price": "160.00",
      "new_price": "95.20",
      "timestamp": "2026-01-22T01:32:51.380655",
      "url": "https://www.johnlewis.com/gallery-direct-carmel-arched-metal-frame-window-wall-mirror-90-x-60cm/p111822498"
    },
    {
      "site": "johnlewis_com",
      "product": "KG Kurt Geiger Telling 2 Suede Knee High Boots",
      "percentage": 40.2,
      "old_price": "199.00",
      "new_price": "119.00",
      "timestamp": "2026-01-22T04:48:56.172496",
      "url": "https://www.johnlewis.com/kg-kurt-geiger-telling-2-suede-knee-high-boots/p113969108"
    },
    {
      "site": "johnlewis_com",
      "product": "Polo Ralph Lauren Cotton Custom Slim Fit Script Logo T-Shirt",
      "percentage": 40.0,
      "old_price": "50.00",
      "new_price": "30.00",
      "timestamp": "2026-01-22T04:48:56.172496",
      "url": "https://www.johnlewis.com/polo-ralph-lauren-cotton-custom-slim-fit-script-logo-t-shirt/p113724126"
    },
    {
      "site": "johnlewis_com",
      "product": "James Lakeland Sleeveless Gathered Maxi Dress, Black",
      "percentage": 39.9,
      "old_price": "199.00",
      "new_price": "119.60",
      "timestamp": "2026-01-22T00:48:54.704820",
      "url": "https://www.johnlewis.com/james-lakeland-sleeveless-gathered-maxi-dress-black/p114436755"
    },
    {
      "site": "johnlewis_com",
      "product": "KG Kurt Geiger Tisha Knee High Boots, Black",
      "percentage": 37.7,
      "old_price": "159.00",
      "new_price": "99.00",
      "timestamp": "2026-01-22T04:48:56.172496",
      "url": "https://www.johnlewis.com/kg-kurt-geiger-tisha-knee-high-boots-black/p112806876"
    },
    {
      "site": "johnlewis_com",
      "product": "Carvela Trento Leather Knee High Boots, Black",
      "percentage": 36.5,
      "old_price": "219.00",
      "new_price": "139.00",
      "timestamp": "2026-01-22T04:48:56.172496",
      "url": "https://www.johnlewis.com/carvela-trento-leather-knee-high-boots-black/p114208296"
    },
    {
      "site": "johnlewis_com",
      "product": "Carvela Riva Leather Chelsea Ankle Boots, Black",
      "percentage": 36.5,
      "old_price": "219.00",
      "new_price": "139.00",
      "timestamp": "2026-01-22T04:48:56.172496",
      "url": "https://www.johnlewis.com/carvela-riva-leather-chelsea-ankle-boots-black/p114476001"
    },
    {
      "site": "johnlewis_com",
      "product": "Tommy Hilfiger Logo Court Trainers",
      "percentage": 36.0,
      "old_price": "90.00",
      "new_price": "57.60",
      "timestamp": "2026-01-22T00:48:54.704820",
      "url": "https://www.johnlewis.com/tommy-hilfiger-logo-court-trainers/p113142662"
    },
    {
      "site": "johnlewis_com",
      "product": "Ro&Zo Floral Polka Dot Long Sleeve V Neck Midi Dress",
      "percentage": 33.9,
      "old_price": "59.00",
      "new_price": "39.00",
      "timestamp": "2026-01-22T00:48:54.704820",
      "url": "https://www.johnlewis.com/ro-zo-floral-polka-dot-long-sleeve-v-neck-midi-dress/p114117325"
    },
    {
      "site": "johnlewis_com",
      "product": "Ro&Zo Petite Floral Midi Dress, Purple/Red",
      "percentage": 33.9,
      "old_price": "59.00",
      "new_price": "39.00",
      "timestamp": "2026-01-22T00:48:54.704820",
      "url": "https://www.johnlewis.com/ro-zo-petite-floral-midi-dress-purple-red/p114026829"
    },
    {
      "site": "johnlewis_com",
      "product": "Ro&Zo Batik Print Maxi Dress, Pink",
      "percentage": 33.9,
      "old_price": "59.00",
      "new_price": "39.00",
      "timestamp": "2026-01-22T00:48:54.704820",
      "url": "https://www.johnlewis.com/ro-zo-batik-print-maxi-dress-pink/p114142677"
    },
    {
      "site": "johnlewis_com",
      "product": "Ro&Zo Petite Floral Tie Back Dress, Red/Multi",
      "percentage": 33.9,
      "old_price": "59.00",
      "new_price": "39.00",
      "timestamp": "2026-01-22T00:48:54.704820",
      "url": "https://www.johnlewis.com/ro-zo-petite-floral-tie-back-dress-red-multi/p113797576"
    },
    {
      "site": "johnlewis_com",
      "product": "HUSH Grace V-Neck Long Sleeve Midi Dress",
      "percentage": 33.7,
      "old_price": "50.00",
      "new_price": "33.15",
      "timestamp": "2026-01-22T00:48:54.704820",
      "url": "https://www.johnlewis.com/hush-grace-v-neck-long-sleeve-midi-dress/p114133973"
    },
    {
      "site": "johnlewis_com",
      "product": "Mint Velvet Floral Appliqué Maxi Dress, Navy Blue",
      "percentage": 33.7,
      "old_price": "89.00",
      "new_price": "59.00",
      "timestamp": "2026-01-22T00:48:54.704820",
      "url": "https://www.johnlewis.com/mint-velvet-floral-applique-maxi-dress-navy-blue/p113886056"
    },
    {
      "site": "johnlewis_com",
      "product": "Ro&Zo Petite Houndstooth Dropped Waist Jersey Dress",
      "percentage": 33.7,
      "old_price": "89.00",
      "new_price": "59.00",
      "timestamp": "2026-01-22T00:48:54.704820",
      "url": "https://www.johnlewis.com/ro-zo-petite-houndstooth-dropped-waist-jersey-dress/p114408411"
    },
    {
      "site": "pigletinbed_com",
      "product": "Cinnamon & Peach Colour Drenched Gingham Linen Blend Duvet Cover",
      "percentage": 33.5,
      "old_price": "167.00",
      "new_price": "111.00",
      "timestamp": "2026-01-22T04:48:18.363429",
      "url": "https://www.pigletinbed.com/products/cinnamon-peach-colour-drenched-gingham-linen-blend-duvet-cover"
    },
    {
      "site": "johnlewis_com",
      "product": "KG Kurt Geiger Fate Faux Leather Fold Over Knee Boots, Black",
      "percentage": 33.5,
      "old_price": "179.00",
      "new_price": "119.00",
      "timestamp": "2026-01-22T04:48:56.172496",
      "url": "https://www.johnlewis.com/kg-kurt-geiger-fate-faux-leather-fold-over-knee-boots-black/p114098032"
    },
    {
      "site": "johnlewis_com",
      "product": "Aspinal of London Slim Leather Postman Messenger Bag, Navy",
      "percentage": 33.3,
      "old_price": "297.00",
      "new_price": "198.00",
      "timestamp": "2026-01-22T00:48:54.704820",
      "url": "https://www.johnlewis.com/aspinal-of-london-slim-leather-postman-messenger-bag-navy/p113971994"
    },
    {
      "site": "johnlewis_com",
      "product": "Joie Baby Nitro Pushchair, Coal",
      "percentage": 33.3,
      "old_price": "75.00",
      "new_price": "50.00",
      "timestamp": "2026-01-22T00:48:54.704820",
      "url": "https://www.johnlewis.com/joie-baby-nitro-pushchair-coal/p109988413"
    },
    {
      "site": "johnlewis_com",
      "product": "Issey Miyake Le Sel d'Issey Eau de Toilette 50ml Fragrance Gift Set",
      "percentage": 33.0,
      "old_price": "73.00",
      "new_price": "48.91",
      "timestamp": "2026-01-22T00:48:54.704820",
      "url": "https://www.johnlewis.com/issey-miyake-le-sel-dissey-eau-de-toilette-50ml-fragrance-gift-set/p114246720"
    },
    {
      "site": "johnlewis_com",
      "product": "Samsung Series 5 WW80CGC04DAB Freestanding Washing Machine, AI Energy, 8kg Load, 1400rpm, Black",
      "percentage": 32.8,
      "old_price": "549.00",
      "new_price": "369.00",
      "timestamp": "2026-01-22T00:48:54.704820",
      "url": "https://www.johnlewis.com/samsung-series-5-ww80cgc04dab-freestanding-washing-machine-ai-energy-8kg-load-1400rpm-black/p111200328"
    },
    {
      "site": "fenwick_co_uk",
      "product": "Brynn Bardot Knitted Top Black",
      "percentage": 31.0,
      "old_price": "29.00",
      "new_price": "20.00",
      "timestamp": "2026-01-22T04:48:39.399202",
      "url": "https://fenwick.co.uk/products/forever-new-black-brynn-bardot-knitted-top-kn7438"
    },
    {
      "site": "fenwick_co_uk",
      "product": "Cassidy One Shoulder Midi Dress Brown",
      "percentage": 30.6,
      "old_price": "62.00",
      "new_price": "43.00",
      "timestamp": "2026-01-22T04:48:39.399202",
      "url": "https://fenwick.co.uk/products/forever-new-brown-cassidy-one-shoulder-plisse-midi-dress-jdc4805"
    },
    {
      "site": "fenwick_co_uk",
      "product": "Mandy Bardot Ruffle Mini Dress Pink",
      "percentage": 30.4,
      "old_price": "46.00",
      "new_price": "32.00",
      "timestamp": "2026-01-22T04:48:39.399202",
      "url": "https://fenwick.co.uk/products/forever-new-pink-mandy-bardot-ruffle-mini-dress-drcz20736"
    },
    {
      "site": "johnlewis_com",
      "product": "Ro&Zo Petite Anya Blurred Floral Dress, Pink/Multi",
      "percentage": 30.3,
      "old_price": "99.00",
      "new_price": "69.00",
      "timestamp": "2026-01-22T00:48:54.704820",
      "url": "https://www.johnlewis.com/ro-zo-petite-anya-blurred-floral-dress-pink-multi/p113599014"
    },
    {
      "site": "fenwick_co_uk",
      "product": "Vivian Asymmetric Twist Maxi Dress Brown",
      "percentage": 30.3,
      "old_price": "66.00",
      "new_price": "46.00",
      "timestamp": "2026-01-22T04:48:39.399202",
      "url": "https://fenwick.co.uk/products/forever-new-brown-vivian-asymmetric-twist-maxi-dress-jd4815"
    },
    {
      "site": "johnlewis_com",
      "product": "Jigsaw Lea Pure Leather Jeans, Black",
      "percentage": 30.0,
      "old_price": "369.00",
      "new_price": "258.30",
      "timestamp": "2026-01-22T00:48:54.704820",
      "url": "https://www.johnlewis.com/jigsaw-lea-pure-leather-jeans-black/p114419231"
    },
    {
      "site": "johnlewis_com",
      "product": "Speedo Essential 16\" Swim Shorts, Grey Lead",
      "percentage": 30.0,
      "old_price": "23.00",
      "new_price": "16.10",
      "timestamp": "2026-01-22T00:48:54.704820",
      "url": "https://www.johnlewis.com/speedo-essential-16-inch-swim-shorts-grey-lead/p113983014"
    },
    {
      "site": "johnlewis_com",
      "product": "Maxi-Cosi Quartz 360 Car Seat, Authentic Graphite",
      "percentage": 30.0,
      "old_price": "249.99",
      "new_price": "174.99",
      "timestamp": "2026-01-22T00:48:54.704820",
      "url": "https://www.johnlewis.com/maxi-cosi-quartz-360-car-seat-authentic-graphite/p112653916"
    },
    {
      "site": "johnlewis_com",
      "product": "Maxi-Cosi Pearl 360 Pro i-Size Car Seat",
      "percentage": 30.0,
      "old_price": "299.99",
      "new_price": "209.99",
      "timestamp": "2026-01-22T00:48:54.704820",
      "url": "https://www.johnlewis.com/maxi-cosi-pearl-360-pro-i-size-car-seat/p113724591"
    },
    {
      "site": "fenwick_co_uk",
      "product": "Zahra 2 in 1 Mini Dress Black",
      "percentage": 30.0,
      "old_price": "60.00",
      "new_price": "42.00",
      "timestamp": "2026-01-22T04:48:39.399202",
      "url": "https://fenwick.co.uk/products/forever-new-black-zahra-2-in-1-mini-dress-jd4809"
    },
    {
      "site": "fenwick_co_uk",
      "product": "Kylee Draped Midi Dress Brown",
      "percentage": 30.0,
      "old_price": "70.00",
      "new_price": "49.00",
      "timestamp": "2026-01-22T04:48:39.399202",
      "url": "https://fenwick.co.uk/products/forever-new-brown-kylee-draped-midi-dress-drcz20956"
    },
    {
      "site": "johnlewis_com",
      "product": "Tommee Tippee UltraLight NightGlow Soothers, 0-6m, Pack of 2, Multi",
      "percentage": 29.9,
      "old_price": "9.99",
      "new_price": "7.00",
      "timestamp": "2026-01-22T01:32:51.380655",
      "url": "https://www.johnlewis.com/tommee-tippee-ultralight-nightglow-soothers-0-6m-pack-of-2-multi/p114362229"
    },
    {
      "site": "fenwick_co_uk",
      "product": "Brielle Fit and Flare Knitted Mini Dress Black",
      "percentage": 29.9,
      "old_price": "77.00",
      "new_price": "54.00",
      "timestamp": "2026-01-22T04:48:39.399202",
      "url": "https://fenwick.co.uk/products/forever-new-black-brielle-fit-and-flare-knitted-mini-dress-kn7309"
    },
    {
      "site": "fenwick_co_uk",
      "product": "Cassie Single Breasted Coatigan Brown",
      "percentage": 29.8,
      "old_price": "57.00",
      "new_price": "40.00",
      "timestamp": "2026-01-22T04:48:39.399202",
      "url": "https://fenwick.co.uk/products/forever-new-brown-cassie-single-breasted-coatigan-ja8364"
    },
    {
      "site": "johnlewis_com",
      "product": "Carvela Bello Suede Ankle Boots, Brown",
      "percentage": 29.6,
      "old_price": "169.00",
      "new_price": "119.00",
      "timestamp": "2026-01-22T04:48:56.172496",
      "url": "https://www.johnlewis.com/carvela-bello-suede-ankle-boots-brown/p113930872"
    },
    {
      "site": "johnlewis_com",
      "product": "Chicco Next2Me Magic Evo Cot",
      "percentage": 29.6,
      "old_price": "199.00",
      "new_price": "140.00",
      "timestamp": "2026-01-22T00:48:54.704820",
      "url": "https://www.johnlewis.com/chicco-next2me-magic-evo-cot/p112247951"
    },
    {
      "site": "fenwick_co_uk",
      "product": "Aubrey Sleeveless Printed Midi Dress Pink",
      "percentage": 29.6,
      "old_price": "54.00",
      "new_price": "38.00",
      "timestamp": "2026-01-22T04:48:39.399202",
      "url": "https://fenwick.co.uk/products/forever-new-pink-aubrey-sleeveless-printed-midi-dress-dr20422"
    },
    {
      "site": "johnlewis_com",
      "product": "Ro&Zo Cotton Poplin Twist Front Dress",
      "percentage": 29.0,
      "old_price": "69.00",
      "new_price": "49.00",
      "timestamp": "2026-01-22T00:48:54.704820",
      "url": "https://www.johnlewis.com/ro-zo-cotton-poplin-twist-front-dress/p113694749"
    },
    {
      "site": "johnlewis_com",
      "product": "Samsung Series 5 WW80CGC04DAE Freestanding Washing Machine, AI Energy, 8kg Load, 1400rpm, White",
      "percentage": 28.9,
      "old_price": "519.00",
      "new_price": "369.00",
      "timestamp": "2026-01-22T00:48:54.704820",
      "url": "https://www.johnlewis.com/samsung-series-5-ww80cgc04dae-freestanding-washing-machine-ai-energy-8kg-load-1400rpm-white/p111200327"
    },
    {
      "site": "johnlewis_com",
      "product": "Hackett London Sport Cotton Short Sleeved T-Shirt, Mint Green",
      "percentage": 28.6,
      "old_price": "45.50",
      "new_price": "32.50",
      "timestamp": "2026-01-22T04:48:56.172496",
      "url": "https://www.johnlewis.com/hackett-london-sport-cotton-short-sleeved-t-shirt-mint-green/p114386319"
    },
    {
      "site": "johnlewis_com",
      "product": "Cath Kidston Orange Blossom Hand Creams, Set of 3",
      "percentage": 28.6,
      "old_price": "5.60",
      "new_price": "4.00",
      "timestamp": "2026-01-22T00:48:54.704820",
      "url": "https://www.johnlewis.com/cath-kidston-orange-blossom-hand-creams-set-of-3/p113030133"
    },
    {
      "site": "johnlewis_com",
      "product": "DockATot Deluxe+ Baby Pod, 0-8 months",
      "percentage": 28.6,
      "old_price": "91.00",
      "new_price": "65.00",
      "timestamp": "2026-01-22T01:32:51.380655",
      "url": "https://www.johnlewis.com/dockatot-deluxe-baby-pod-0-8-months/p110550099"
    },
    {
      "site": "fenwick_co_uk",
      "product": "Becca Scalloped Neck Blouse",
      "percentage": 28.6,
      "old_price": "35.00",
      "new_price": "25.00",
      "timestamp": "2026-01-22T04:48:39.399202",
      "url": "https://fenwick.co.uk/products/forever-new-multi-becca-scalloped-neck-blouse-sh13662"
    },
    {
      "site": "johnlewis_com",
      "product": "Mint Velvet Metallic Midi Shirt Dress, Gold",
      "percentage": 28.2,
      "old_price": "110.00",
      "new_price": "79.00",
      "timestamp": "2026-01-22T00:48:54.704820",
      "url": "https://www.johnlewis.com/mint-velvet-metallic-midi-shirt-dress-gold/p114269803"
    },
    {
      "site": "bugaboo_com",
      "product": "Bugaboo Fox 5/Cameleon 3 raincover",
      "percentage": 28.0,
      "old_price": "44.95",
      "new_price": "32.36",
      "timestamp": "2026-01-22T00:33:27.432021",
      "url": "https://www.bugaboo.com/gb-en/accessories/rain-covers/bugaboo-fox-5-cameleon-3-raincover-230550.html"
    },
    {
      "site": "fenwick_co_uk",
      "product": "Oxford Square Oxford Pillowcase",
      "percentage": 28.0,
      "old_price": "75.00",
      "new_price": "54.00",
      "timestamp": "2026-01-22T04:48:39.399202",
      "url": "https://fenwick.co.uk/products/other-blue-oxford-square-oxford-pillowcase"
    },
    {
      "site": "fenwick_co_uk",
      "product": "Oxford Standard Housewife Pillowcase Pair",
      "percentage": 28.0,
      "old_price": "89.00",
      "new_price": "64.08",
      "timestamp": "2026-01-22T04:48:39.399202",
      "url": "https://fenwick.co.uk/products/other-rosette-oxford-standard-housewife-pillowcase-pair-rloxfordrosettepcp"
    },
    {
      "site": "fenwick_co_uk",
      "product": "Oxford Standard Oxford Pillowcase",
      "percentage": 28.0,
      "old_price": "75.00",
      "new_price": "54.00",
      "timestamp": "2026-01-22T04:48:39.399202",
      "url": "https://fenwick.co.uk/products/other-rosette-oxford-standard-oxford-pillowcase-rloxfordrosettepc"
    },
    {
      "site": "fenwick_co_uk",
      "product": "Oxford Fitted Sheet",
      "percentage": 28.0,
      "old_price": "139.00",
      "new_price": "100.08",
      "timestamp": "2026-01-22T04:48:39.399202",
      "url": "https://fenwick.co.uk/products/other-rosette-oxford-fitted-sheet-rloxfordrosetteftd"
    },
    {
      "site": "fenwick_co_uk",
      "product": "Langdon Oxford Pillowcase",
      "percentage": 28.0,
      "old_price": "95.00",
      "new_price": "68.40",
      "timestamp": "2026-01-22T04:48:39.399202",
      "url": "https://fenwick.co.uk/products/other-whitenavy-langdon-oxford-pillowcase-pair-rllangopcwhitenavy"
    },
    {
      "site": "fenwick_co_uk",
      "product": "Polo Player Standard Pillowcase",
      "percentage": 28.0,
      "old_price": "49.00",
      "new_price": "35.28",
      "timestamp": "2026-01-22T04:48:39.399202",
      "url": "https://fenwick.co.uk/products/other-white-polo-player-white-standard-pillowcase-rlrlplpcwhite"
    },
    {
      "site": "fenwick_co_uk",
      "product": "Langdon Pillowcase Pair",
      "percentage": 28.0,
      "old_price": "115.00",
      "new_price": "82.80",
      "timestamp": "2026-01-22T04:48:39.399202",
      "url": "https://fenwick.co.uk/products/other-navy-langdon-pillowcase-pair-rllangpcnavy"
    },
    {
      "site": "fenwick_co_uk",
      "product": "Oxford Duvet Cover",
      "percentage": 28.0,
      "old_price": "215.00",
      "new_price": "154.80",
      "timestamp": "2026-01-22T04:48:39.399202",
      "url": "https://fenwick.co.uk/products/other-rosette-oxford-duvet-cover"
    },
    {
      "site": "fenwick_co_uk",
      "product": "Langdon Standard Oxford Pillowcase",
      "percentage": 28.0,
      "old_price": "95.00",
      "new_price": "68.40",
      "timestamp": "2026-01-22T04:48:39.399202",
      "url": "https://fenwick.co.uk/products/other-whitesilver-langdon-standard-oxford-pillowcase-rllangdonwhitesilverpc"
    },
    {
      "site": "fenwick_co_uk",
      "product": "Doncaster Oxford Pillowcase",
      "percentage": 28.0,
      "old_price": "89.00",
      "new_price": "64.08",
      "timestamp": "2026-01-22T04:48:39.399202",
      "url": "https://fenwick.co.uk/products/other-capetan-doncaster-oxford-pillowcase-rldoncopccapetan"
    },
    {
      "site": "fenwick_co_uk",
      "product": "Polo Player Duvet Cover Collection",
      "percentage": 28.0,
      "old_price": "129.00",
      "new_price": "92.88",
      "timestamp": "2026-01-22T04:48:39.399202",
      "url": "https://fenwick.co.uk/products/other-pink-pinksky-polo-player-pink-sky-duvet-cover-rlrlpldcpinksky"
    },
    {
      "site": "fenwick_co_uk",
      "product": "Polo Player Standard Pillowcase Collection",
      "percentage": 28.0,
      "old_price": "49.00",
      "new_price": "35.28",
      "timestamp": "2026-01-22T04:48:39.399202",
      "url": "https://fenwick.co.uk/products/other-navy-newport-polo-player-newport-standard-pillowcase-rlrlplpcnewport"
    },
    {
      "site": "fenwick_co_uk",
      "product": "Doncaster Standard Oxford Pillowcase",
      "percentage": 28.0,
      "old_price": "89.00",
      "new_price": "64.08",
      "timestamp": "2026-01-22T04:48:39.399202",
      "url": "https://fenwick.co.uk/products/other-dark-green-doncaster-standard-oxford-pillowcase-rldoncpcdarkgreen"
    },
    {
      "site": "fenwick_co_uk",
      "product": "Polo Player Fitted Sheet Collection",
      "percentage": 28.0,
      "old_price": "75.00",
      "new_price": "54.00",
      "timestamp": "2026-01-22T04:48:39.399202",
      "url": "https://fenwick.co.uk/products/other-pink-pinksky-polo-player-pink-sky-fitted-sheet-rlrlpldhpinksky"
    },
    {
      "site": "fenwick_co_uk",
      "product": "Langdon Flat Sheet",
      "percentage": 28.0,
      "old_price": "259.00",
      "new_price": "186.48",
      "timestamp": "2026-01-22T04:48:39.399202",
      "url": "https://fenwick.co.uk/products/other-whitenavy-langdon-flat-sheet-rllangfltwhitenavy"
    },
    {
      "site": "fenwick_co_uk",
      "product": "Langdon Fitted Sheet",
      "percentage": 28.0,
      "old_price": "169.00",
      "new_price": "121.68",
      "timestamp": "2026-01-22T04:48:39.399202",
      "url": "https://fenwick.co.uk/products/other-silver-langdon-fitted-sheet-rllangdon624silverftd"
    },
    {
      "site": "fenwick_co_uk",
      "product": "Polo Player Square Pillowcase Collection",
      "percentage": 28.0,
      "old_price": "49.00",
      "new_price": "35.28",
      "timestamp": "2026-01-22T04:48:39.399202",
      "url": "https://fenwick.co.uk/products/other-navy-newport-polo-player-newport-square-pillowcase-rlrlplpcsnewport"
    },
    {
      "site": "fenwick_co_uk",
      "product": "Langdon Fitted Sheet Collection",
      "percentage": 28.0,
      "old_price": "169.00",
      "new_price": "121.68",
      "timestamp": "2026-01-22T04:48:39.399202",
      "url": "https://fenwick.co.uk/products/other-navy-langdon-fitted-sheet-rllangdhnavy"
    },
    {
      "site": "fenwick_co_uk",
      "product": "Doncaster Duvet Cover",
      "percentage": 28.0,
      "old_price": "359.00",
      "new_price": "258.48",
      "timestamp": "2026-01-22T04:48:39.399202",
      "url": "https://fenwick.co.uk/products/other-dark-green-doncaster-duvet-cover-rldoncdcdarkgreen"
    },
    {
      "site": "fenwick_co_uk",
      "product": "Langdon Standard Housewife Pillowcase Pair",
      "percentage": 28.0,
      "old_price": "115.00",
      "new_price": "82.80",
      "timestamp": "2026-01-22T04:48:39.399202",
      "url": "https://fenwick.co.uk/products/other-silver-langdon-standard-housewife-pillowcase-pair-rllangdon624silverpcp"
    },
    {
      "site": "fenwick_co_uk",
      "product": "Langdon Duvet Cover Collection",
      "percentage": 28.0,
      "old_price": "385.00",
      "new_price": "277.20",
      "timestamp": "2026-01-22T04:48:39.399202",
      "url": "https://fenwick.co.uk/products/other-sil-silver-langdon-duvet-cover-rllangdcsilver"
    },
    {
      "site": "fenwick_co_uk",
      "product": "Polo Player Flat Sheet",
      "percentage": 28.0,
      "old_price": "125.00",
      "new_price": "90.00",
      "timestamp": "2026-01-22T04:48:39.399202",
      "url": "https://fenwick.co.uk/products/other-white-polo-player-white-flat-sheet-rlrlplfltwhite"
    },
    {
      "site": "fenwick_co_uk",
      "product": "Polo Player Square Pillowcase",
      "percentage": 28.0,
      "old_price": "49.00",
      "new_price": "35.28",
      "timestamp": "2026-01-22T04:48:39.399202",
      "url": "https://fenwick.co.uk/products/other-grey-andover-polo-player-andover-square-pillowcase-rlrlplpcsandover"
    },
    {
      "site": "fenwick_co_uk",
      "product": "Langdon Square Oxford Pillowcase",
      "percentage": 28.0,
      "old_price": "95.00",
      "new_price": "68.40",
      "timestamp": "2026-01-22T04:48:39.399202",
      "url": "https://fenwick.co.uk/products/other-whitesilver-langdon-square-oxford-pillowcase-rllangdonwhitesilverpc"
    },
    {
      "site": "fenwick_co_uk",
      "product": "Langdon Square Housewife Pillowcase Pair",
      "percentage": 28.0,
      "old_price": "115.00",
      "new_price": "82.80",
      "timestamp": "2026-01-22T04:48:39.399202",
      "url": "https://fenwick.co.uk/products/other-silver-langdon-square-housewife-pillowcase-pair-rllangdon624silverpcp"
    },
    {
      "site": "fenwick_co_uk",
      "product": "Oxford Flat Sheet Collection",
      "percentage": 28.0,
      "old_price": "209.00",
      "new_price": "150.48",
      "timestamp": "2026-01-22T04:48:39.399202",
      "url": "https://fenwick.co.uk/products/other-blue-oxford-flat-sheet-rloxfordblueflt"
    },
    {
      "site": "fenwick_co_uk",
      "product": "Doncaster Square Oxford Pillowcase",
      "percentage": 28.0,
      "old_price": "89.00",
      "new_price": "64.08",
      "timestamp": "2026-01-22T04:48:39.399202",
      "url": "https://fenwick.co.uk/products/other-silver-doncaster-square-oxford-pillowcase-rldoncastersilverpc"
    },
    {
      "site": "fenwick_co_uk",
      "product": "Oxford Flat Sheet",
      "percentage": 28.0,
      "old_price": "209.00",
      "new_price": "150.48",
      "timestamp": "2026-01-22T04:48:39.399202",
      "url": "https://fenwick.co.uk/products/other-rosette-oxford-flat-sheet"
    },
    {
      "site": "fenwick_co_uk",
      "product": "Polo Player Hand Towel",
      "percentage": 28.0,
      "old_price": "29.00",
      "new_price": "20.88",
      "timestamp": "2026-01-22T04:48:39.399202",
      "url": "https://fenwick.co.uk/products/other-pale-oak-polo-player-pale-oak-hand-towel-rlpolobtpaleoak"
    },
    {
      "site": "fenwick_co_uk",
      "product": "Polo Player Guest Towel",
      "percentage": 28.0,
      "old_price": "19.00",
      "new_price": "13.68",
      "timestamp": "2026-01-22T04:48:39.399202",
      "url": "https://fenwick.co.uk/products/other-newport-navy-polo-player-newport-navy-guest-towel-rlpolobtnewportnavy"
    },
    {
      "site": "fenwick_co_uk",
      "product": "Polo Player Mitt",
      "percentage": 28.0,
      "old_price": "12.00",
      "new_price": "8.64",
      "timestamp": "2026-01-22T04:48:39.399202",
      "url": "https://fenwick.co.uk/products/other-andover-heather-polo-player-andover-heather-mitt-rlpolomitandoverheather"
    }
  ]
}